i2a_django_tools/__init__.py
i2a_django_tools/database.py
i2a_django_tools/exceptions.py
i2a_django_tools/expressions.py
i2a_django_tools/fields.py
i2a_django_tools/filters.py
i2a_django_tools/handlers.py
i2a_django_tools/management.py
i2a_django_tools/models.py
i2a_django_tools/paginators.py
i2a_django_tools/testing.py
i2a_django_tools/mixins/__init__.py
i2a_django_tools/mixins/admin_filters.py
i2a_django_tools/mixins/admin_mixins.py
i2a_django_tools/mixins/model_mixins.py
i2a_django_tools/reports/__init__.py
i2a_django_tools/reports/pdf_generator.py
i2a_django_tools/reports/report_serializers.py
i2a_django_tools/reports/report_service.py
i2a_django_tools/serializers/__init__.py
i2a_django_tools/serializers/expression_methods_mapping.py
i2a_django_tools/serializers/serializers.py
i2a_django_tools/serializers/validation_service.py
i2a_django_tools/serializers/validators.py
i2a_django_tools-2.1.2.dist-info/METADATA
i2a_django_tools-2.1.2.dist-info/WHEEL
i2a_django_tools-2.1.2.dist-info/top_level.txt
i2a_django_tools-2.1.2.dist-info/RECORD
