Metadata-Version: 2.1
Name: i2a-django-tools
Version: 2.1.2
Summary: Sdk for i2a django tools
Download-URL: https://pypi.org/project/i2a_django_tools/
Author: i2a Solutions Inc.
Author-email: msyta@i2asolutions.com
License: MIT
Keywords: I2A Django Tools,I2A,Python 3,I2A Tools SDK
Platform: UNKNOWN
